[
  {
    "id": 12,
    "title": "캠프1 플러스",
    "brand": "kovea",
    "price": 76600,
    "link": "https://brand.naver.com/kovea/products/5097164717?NaPm=ct%3Dl61xsga0%7Cci%3D9da319b42af21c107ed8d2162d6f17c821ce02b5%7Ctr%3Dslsc%7Csn%3D761448%7Chk%3Decf862ff48e62678209ff556c64367d1511361b0"
  },
  {
    "id": 13,
    "title": "파워스토브W",
    "brand": "helinox",
    "price": 264000,
    "link": "http://www.minimalworks.co.kr/goods/goods_view.php?goodsNo=186"
  },
  {
    "id": 14,
    "title": "GARDEN & CAMP 버너",
    "brand": "Snowpeak",
    "price": 138000,
    "link": "http://www.eoutdoors.co.kr/shop/shopdetail.html?branduid=241432&ref=naver_open&NaPm=ct%3Dl61y1chs%7Cci%3D899f3d72881a7046254d29873a974115a92d2908%7Ctr%3Dslsl%7Csn%3D223686%7Chk%3D3a1607e4ea2aff160caa5fe76cf63d100e084b13"
  }
]